MANIFEST.in
README.md
setup.py
pocsuite/__init__.py
pocsuite/__init__.pyc
pocsuite/pocsuite_attack.py
pocsuite/pocsuite_cli.py
pocsuite/pocsuite_cli.pyc
pocsuite/pocsuite_console.py
pocsuite/pocsuite_verify.py
pocsuite.egg-info/PKG-INFO
pocsuite.egg-info/SOURCES.txt
pocsuite.egg-info/dependency_links.txt
pocsuite.egg-info/entry_points.txt
pocsuite.egg-info/not-zip-safe
pocsuite.egg-info/requires.txt
pocsuite.egg-info/top_level.txt
pocsuite/api/__init__.py
pocsuite/api/__init__.pyc
pocsuite/api/cannon.py
pocsuite/api/packet.py
pocsuite/api/poc.py
pocsuite/api/poc.pyc
pocsuite/api/rcGen.py
pocsuite/api/rcGen.pyc
pocsuite/api/request.py
pocsuite/api/request.pyc
pocsuite/api/seebug.py
pocsuite/api/utils.py
pocsuite/api/utils.pyc
pocsuite/api/webshell.py
pocsuite/api/x.py
pocsuite/api/x.pyc
pocsuite/api/zoomeye.py
pocsuite/data/password-top100.txt
pocsuite/data/password-top1000.txt
pocsuite/data/token.conf
pocsuite/data/user-agents.txt
pocsuite/lib/__init__.py
pocsuite/lib/__init__.pyc
pocsuite/lib/controller/__init__.py
pocsuite/lib/controller/__init__.pyc
pocsuite/lib/controller/check.py
pocsuite/lib/controller/check.pyc
pocsuite/lib/controller/controller.py
pocsuite/lib/controller/controller.pyc
pocsuite/lib/controller/setpoc.py
pocsuite/lib/controller/setpoc.pyc
pocsuite/lib/core/__init__.py
pocsuite/lib/core/__init__.pyc
pocsuite/lib/core/common.py
pocsuite/lib/core/common.pyc
pocsuite/lib/core/consoles.py
pocsuite/lib/core/convert.py
pocsuite/lib/core/convert.pyc
pocsuite/lib/core/data.py
pocsuite/lib/core/data.pyc
pocsuite/lib/core/datatype.py
pocsuite/lib/core/datatype.pyc
pocsuite/lib/core/defaults.py
pocsuite/lib/core/defaults.pyc
pocsuite/lib/core/enums.py
pocsuite/lib/core/enums.pyc
pocsuite/lib/core/exception.py
pocsuite/lib/core/exception.pyc
pocsuite/lib/core/handlejson.py
pocsuite/lib/core/handlejson.pyc
pocsuite/lib/core/log.py
pocsuite/lib/core/log.pyc
pocsuite/lib/core/option.py
pocsuite/lib/core/option.pyc
pocsuite/lib/core/poc.py
pocsuite/lib/core/poc.pyc
pocsuite/lib/core/register.py
pocsuite/lib/core/register.pyc
pocsuite/lib/core/revision.py
pocsuite/lib/core/revision.pyc
pocsuite/lib/core/settings.py
pocsuite/lib/core/settings.pyc
pocsuite/lib/core/threads.py
