Metadata-Version: 1.0
Name: pocsuite
Version: 2.0.8
Summary: Pocsuite is an open-sourced remote vulnerability testing framework developed by the Knownsec Security Team.
Home-page: http://pocsuite.org
Author: Knownsec Security Team
Author-email: s1@seebug.org
License: GPL 2.0
Keywords: PoC,Exp,Pocsuite
Platform: UNKNOWN
